<?xml version="1.0" encoding="UTF-8"?>
<PlantModel>
	<PlantInformation SchemaVersion="3.2.0" OriginatingSystem="POD" Date="2009-01-01" Time="01:02:03" Is3D="yes" Units="mm" Discipline="Piping">
		<UnitsOfMeasure Distance="m" Angle="Degree" Area="SquareMetre" Volume="CubicMetre" Temperature="DegreeCelsius" Pressure="Bar" Weight="Kilogram"/>
	</PlantInformation>
	<PipingNetworkSystem ID="PNSystem1" Tag="663RBW-1006-1_-1C0JL-N-0MM" Specification="1C0JL">
		<Extent>
			<Min X="596999.990000" Y="1510126.270000" Z="5021.600000"/>
			<Max X="597750.120000" Y="1511500.030000" Z="5746.520000"/>
		</Extent>
		<PipingNetworkSegment ID="PNSegment1" Tag="Segment1" Specification="1C0JL">
			<GenericAttributes Number="2">
				<NominalDiameter Value="2.000000" Units="in"/>
				<DirectionOfFlow Value="2"/>
			</GenericAttributes>
			<PipingComponent ID="XMP_5" ComponentClass="WeldNeckFlange" StockNumber="3A507QBC2A">
				<ConnectionPoints NumPoints="3">
					<Node>
						<Position>
							<Location X="596999.990000" Y="1510161.935000" Z="5204.750000"/>
							<Axis X="0.000000" Y="-1.000000" Z="0.000000"/>
							<Reference X="0.000000" Y="-1.000000" Z="0.000000"/>
						</Position>
					</Node>
					<Node>
						<Position>
							<Location X="596999.990000" Y="1510126.270000" Z="5204.750000"/>
						</Position>
						<NominalDiameter Value="2.000000" Units="in"/>
					</Node>
					<Node>
						<Position>
							<Location X="596999.990000" Y="1510197.600000" Z="5204.750000"/>
						</Position>
						<NominalDiameter Value="2.000000" Units="in"/>
					</Node>
				</ConnectionPoints>
			</PipingComponent>
		
			<Pipe ID="XMP_18" ComponentClass="Pipe" StockNumber="1A504Q*C2A">
				<Association Type="refers to" ItemID="XMP_9"/>
				<Association Type="refers to" ItemID="XMP_13"/>
				<Association Type="refers to" ItemID="XMP_14"/>
				<Association Type="refers to" ItemID="XMP_15"/>
				<Association Type="refers to" ItemID="XMP_17"/>
				<ConnectionPoints NumPoints="3">
					<Node>
						<Position>
							<Location X="596999.995000" Y="1510535.985000" Z="5204.880000"/>
						</Position>
					</Node>
					<Node>
						<Position>
							<Location X="596999.990000" Y="1510197.600000" Z="5204.750000"/>
						</Position>
						<NominalDiameter Value="2.000000" Units="in"/>
					</Node>
					<Node>
						<Position>
							<Location X="597000.000000" Y="1510874.370000" Z="5205.010000"/>
						</Position>
						<NominalDiameter Value="2.000000" Units="in"/>
					</Node>
				</ConnectionPoints>
			</Pipe>
		
			<PipingComponent ID="XMP_21" ComponentClass="PipingTee" StockNumber="663-SRY-6004A">
				<ConnectionPoints NumPoints="4">
					<Node>
						<Position>
							<Location X="597000.000000" Y="1511094.360000" Z="5205.010000"/>
							<Axis X="0.000000" Y="-1.000000" Z="0.000000"/>
							<Reference X="0.000000" Y="0.707086" Z="0.707128"/>
						</Position>
					</Node>
					<Node>
						<Position>
							<Location X="597000.000000" Y="1510874.370000" Z="5205.010000"/>
						</Position>
						<NominalDiameter Value="2.000000" Units="in"/>
					</Node>
					<Node>
						<Position>
							<Location X="597000.000000" Y="1511164.360000" Z="5205.010000"/>
						</Position>
						<NominalDiameter Value="2.000000" Units="in"/>
					</Node>
					<Node>
						<Position>
							<Location X="597000.000000" Y="1510924.390000" Z="5035.030000"/>
						</Position>
						<NominalDiameter Value="2.000000" Units="in"/>
					</Node>
				</ConnectionPoints>
			</PipingComponent>
		
			<Pipe ID="XMP_30" ComponentClass="Pipe" StockNumber="1A504Q*C2A">
				<ConnectionPoints NumPoints="3">
					<Node>
						<Position>
							<Location X="597000.000000" Y="1511294.105000" Z="5205.010000"/>
						</Position>
					</Node>
					<Node>
						<Position>
							<Location X="597000.000000" Y="1511164.360000" Z="5205.010000"/>
						</Position>
						<NominalDiameter Value="2.000000" Units="in"/>
					</Node>
					<Node>
						<Position>
							<Location X="597000.000000" Y="1511423.850000" Z="5205.010000"/>
						</Position>
						<NominalDiameter Value="2.000000" Units="in"/>
					</Node>
				</ConnectionPoints>
			</Pipe>
		
			<PipingComponent ID="XMP_32" ComponentClass="PipingElbow90" StockNumber="6A605Q*C2A">
				<ConnectionPoints NumPoints="3">
					<Node>
						<Position>
							<Location X="597000.000000" Y="1511500.030000" Z="5205.010000"/>
							<Axis X="0.000000" Y="-1.000000" Z="0.000000"/>
							<Reference X="-1.000000" Y="0.000000" Z="0.000000"/>
						</Position>
					</Node>
					<Node>
						<Position>
							<Location X="597000.000000" Y="1511423.850000" Z="5205.010000"/>
						</Position>
						<NominalDiameter Value="2.000000" Units="in"/>
					</Node>
					<Node>
						<Position>
							<Location X="597076.180000" Y="1511500.030000" Z="5205.010000"/>
						</Position>
						<NominalDiameter Value="2.000000" Units="in"/>
					</Node>
				</ConnectionPoints>
			</PipingComponent>
		
			<PipingComponent ID="XMP_35" ComponentClass="WeldNeckFlange" StockNumber="3A506QBC2A">
				<ConnectionPoints NumPoints="3">
					<Node>
						<Position>
							<Location X="597108.670000" Y="1511500.030000" Z="5205.010000"/>
							<Axis X="1.000000" Y="0.000000" Z="0.000000"/>
							<Reference X="1.000000" Y="0.000000" Z="0.000000"/>
						</Position>
					</Node>
					<Node>
						<Position>
							<Location X="597141.160000" Y="1511500.030000" Z="5205.010000"/>
						</Position>
						<NominalDiameter Value="2.000000" Units="in"/>
					</Node>
					<Node>
						<Position>
							<Location X="597076.180000" Y="1511500.030000" Z="5205.010000"/>
						</Position>
						<NominalDiameter Value="2.000000" Units="in"/>
					</Node>
				</ConnectionPoints>
			</PipingComponent>
		
			<PipingComponent ID="XMP_37" ComponentClass="UNKNOWN-COMPONENT" StockNumber="3P606B*C2A">
				<ConnectionPoints NumPoints="3">
					<Node>
						<Position>
							<Location X="597144.660000" Y="1511500.030000" Z="5205.010000"/>
						</Position>
					</Node>
					<Node>
						<Position>
							<Location X="597142.660000" Y="1511500.030000" Z="5205.010000"/>
						</Position>
						<NominalDiameter Value="2.000000" Units="in"/>
					</Node>
					<Node>
						<Position>
							<Location X="597146.660000" Y="1511500.030000" Z="5205.010000"/>
						</Position>
						<NominalDiameter Value="2.000000" Units="in"/>
					</Node>
				</ConnectionPoints>
			</PipingComponent>
		
			<PipingComponent ID="XMP_42" ComponentClass="GateValve" StockNumber="2A612BCC2A">
				<Position>
					<Location X="597238.560000" Y="1511500.030000" Z="5205.010000"/>
					<Axis X="0.000000" Y="0.000000" Z="1.000000"/>
					<Reference X="1.000000" Y="0.000000" Z="0.000000"/>
				</Position>
				<ConnectionPoints NumPoints="3">
					<Node>
						<Position>
							<Location X="597238.560000" Y="1511500.030000" Z="5205.010000"/>
						</Position>
					</Node>
					<Node>
						<Position>
							<Location X="597148.160000" Y="1511500.030000" Z="5205.010000"/>
						</Position>
						<NominalDiameter Value="2.000000" Units="in"/>
					</Node>
					<Node>
						<Position>
							<Location X="597328.960000" Y="1511500.030000" Z="5205.010000"/>
						</Position>
						<NominalDiameter Value="2.000000" Units="in"/>
					</Node>
				</ConnectionPoints>
			</PipingComponent>
		
			<PipingComponent ID="XMP_45" ComponentClass="WeldNeckFlange" StockNumber="3A506QBC2A">
				<ConnectionPoints NumPoints="3">
					<Node>
						<Position>
							<Location X="597361.445000" Y="1511500.030000" Z="5205.010000"/>
							<Axis X="-1.000000" Y="0.000000" Z="0.000000"/>
							<Reference X="-1.000000" Y="0.000000" Z="0.000000"/>
						</Position>
					</Node>
					<Node>
						<Position>
							<Location X="597328.960000" Y="1511500.030000" Z="5205.010000"/>
						</Position>
						<NominalDiameter Value="2.000000" Units="in"/>
					</Node>
					<Node>
						<Position>
							<Location X="597393.930000" Y="1511500.030000" Z="5205.010000"/>
						</Position>
						<NominalDiameter Value="2.000000" Units="in"/>
					</Node>
				</ConnectionPoints>
			</PipingComponent>
		
			<Pipe ID="XMP_47" ComponentClass="Pipe" StockNumber="1A504Q*C2A">
				<Association Type="refers to" ItemID="XMP_48"/>
				<ConnectionPoints NumPoints="3">
					<Node>
						<Position>
							<Location X="597533.930000" Y="1511500.030000" Z="5205.010000"/>
						</Position>
					</Node>
					<Node>
						<Position>
							<Location X="597393.930000" Y="1511500.030000" Z="5205.010000"/>
						</Position>
						<NominalDiameter Value="2.000000" Units="in"/>
					</Node>
					<Node>
						<Position>
							<Location X="597673.930000" Y="1511500.030000" Z="5205.010000"/>
						</Position>
						<NominalDiameter Value="2.000000" Units="in"/>
					</Node>
				</ConnectionPoints>
			</Pipe>
		
			<PipingComponent ID="XMP_52" ComponentClass="PipingElbow90" StockNumber="6A605Q*C2A">
				<Association Type="refers to" ItemID="XMP_53"/>
				<ConnectionPoints NumPoints="3">
					<Node>
						<Position>
							<Location X="597750.120000" Y="1511500.030000" Z="5205.010000"/>
							<Axis X="-1.000000" Y="0.000000" Z="0.000000"/>
							<Reference X="0.000000" Y="0.000000" Z="-1.000000"/>
						</Position>
					</Node>
					<Node>
						<Position>
							<Location X="597673.930000" Y="1511500.030000" Z="5205.010000"/>
						</Position>
						<NominalDiameter Value="2.000000" Units="in"/>
					</Node>
					<Node>
						<Position>
							<Location X="597750.120000" Y="1511500.030000" Z="5281.200000"/>
						</Position>
						<NominalDiameter Value="2.000000" Units="in"/>
					</Node>
				</ConnectionPoints>
			</PipingComponent>
		
			<Pipe ID="XMP_56" ComponentClass="Pipe" StockNumber="1A504Q*C2A">
				<ConnectionPoints NumPoints="3">
					<Node>
						<Position>
							<Location X="597750.120000" Y="1511500.030000" Z="5391.725000"/>
						</Position>
					</Node>
					<Node>
						<Position>
							<Location X="597750.120000" Y="1511500.030000" Z="5281.200000"/>
						</Position>
						<NominalDiameter Value="2.000000" Units="in"/>
					</Node>
					<Node>
						<Position>
							<Location X="597750.120000" Y="1511500.030000" Z="5502.250000"/>
						</Position>
						<NominalDiameter Value="2.000000" Units="in"/>
					</Node>
				</ConnectionPoints>
			</Pipe>
		
			<PipingComponent ID="XMP_58" ComponentClass="WeldNeckFlange" StockNumber="3A506QBC2A">
				<ConnectionPoints NumPoints="3">
					<Node>
						<Position>
							<Location X="597750.120000" Y="1511500.030000" Z="5534.735000"/>
							<Axis X="0.000000" Y="0.000000" Z="1.000000"/>
							<Reference X="0.000000" Y="0.000000" Z="1.000000"/>
						</Position>
					</Node>
					<Node>
						<Position>
							<Location X="597750.120000" Y="1511500.030000" Z="5567.220000"/>
						</Position>
						<NominalDiameter Value="2.000000" Units="in"/>
					</Node>
					<Node>
						<Position>
							<Location X="597750.120000" Y="1511500.030000" Z="5502.250000"/>
						</Position>
						<NominalDiameter Value="2.000000" Units="in"/>
					</Node>
				</ConnectionPoints>
			</PipingComponent>
		
			<PipingComponent ID="XMP_61" ComponentClass="GateValve" StockNumber="2A612BCC2A">
				<Position>
					<Location X="597750.120000" Y="1511500.030000" Z="5656.870000"/>
					<Axis X="-1.000000" Y="0.000000" Z="0.000000"/>
					<Reference X="0.000000" Y="0.000000" Z="1.000000"/>
				</Position>
				<ConnectionPoints NumPoints="3">
					<Node>
						<Position>
							<Location X="597750.120000" Y="1511500.030000" Z="5656.870000"/>
						</Position>
					</Node>
					<Node>
						<Position>
							<Location X="597750.120000" Y="1511500.030000" Z="5567.220000"/>
						</Position>
						<NominalDiameter Value="2.000000" Units="in"/>
					</Node>
					<Node>
						<Position>
							<Location X="597750.120000" Y="1511500.030000" Z="5746.520000"/>
						</Position>
						<NominalDiameter Value="2.000000" Units="in"/>
					</Node>
				</ConnectionPoints>
			</PipingComponent>
		</PipingNetworkSegment>
		<PipingNetworkSegment ID="PNSegment2" Tag="Segment2" Specification="1C0JL">
			<GenericAttributes Number="1">
				<NominalDiameter Value="2.000000" Units="in"/>
			</GenericAttributes>
			<PipingComponent ID="XMP_25" ComponentClass="PipingCap" StockNumber="4CYLS1">
				<ConnectionPoints NumPoints="3">
					<Node>
						<Position>
							<Location X="597000.000000" Y="1510917.670000" Z="5028.315000"/>
						</Position>
					</Node>
					<Node>
						<Position>
							<Location X="597000.000000" Y="1510924.390000" Z="5035.030000"/>
						</Position>
						<NominalDiameter Value="2.000000" Units="in"/>
					</Node>
					<Node>
						<Position>
							<Location X="597000.000000" Y="1510910.950000" Z="5021.600000"/>
						</Position>
						<NominalDiameter Value="2.000000" Units="in"/>
					</Node>
				</ConnectionPoints>
			</PipingComponent>
		</PipingNetworkSegment>
	</PipingNetworkSystem>
	<PipeSupport ID="XMP_9" Specification="1C0JL" StockNumber="GST-6">
		<Position>
			<Location X="596999.990000" Y="1510499.840000" Z="5204.850000"/>
			<Axis X="0.000000" Y="0.000000" Z="0.000000"/>
			<Reference X="0.000000" Y="0.000000" Z="0.000000"/>
		</Position>
		<Association Type="is associated with" ItemID="XMP_18"/>
		<NominalDiameter Value="2.000000" Units="in"/>
		<ConnectionPoints NumPoints="1">
			<Node>
				<Position>
					<Location X="596999.990000" Y="1510499.840000" Z="5204.850000"/>
					<Axis X="0.000000" Y="0.000000" Z="0.000000"/>
					<Reference X="0.000000" Y="0.000000" Z="0.000000"/>
				</Position>
			</Node>
		</ConnectionPoints>
	</PipeSupport>
	<PipeSupport ID="XMP_13" Specification="1C0JL" StockNumber="TEF2S-1">
		<Position>
			<Location X="596999.990000" Y="1510599.830000" Z="5204.870000"/>
			<Axis X="0.000000" Y="0.000000" Z="0.000000"/>
			<Reference X="0.000000" Y="0.000000" Z="0.000000"/>
		</Position>
		<Association Type="is associated with" ItemID="XMP_18"/>
		<NominalDiameter Value="1.000000" Units="in"/>
		<ConnectionPoints NumPoints="1">
			<Node>
				<Position>
					<Location X="596999.990000" Y="1510599.830000" Z="5204.870000"/>
					<Axis X="0.000000" Y="0.000000" Z="0.000000"/>
					<Reference X="0.000000" Y="0.000000" Z="0.000000"/>
				</Position>
			</Node>
		</ConnectionPoints>
	</PipeSupport>
	<PipeSupport ID="XMP_14" Specification="1C0JL" StockNumber="14-2-07-PE">
		<Position>
			<Location X="596999.990000" Y="1510599.830000" Z="5204.870000"/>
			<Axis X="0.000000" Y="0.000000" Z="0.000000"/>
			<Reference X="0.000000" Y="0.000000" Z="0.000000"/>
		</Position>
		<Association Type="is associated with" ItemID="XMP_18"/>
		<NominalDiameter Value="2.000000" Units="in"/>
		<ConnectionPoints NumPoints="1">
			<Node>
				<Position>
					<Location X="596999.990000" Y="1510599.830000" Z="5204.870000"/>
					<Axis X="0.000000" Y="0.000000" Z="0.000000"/>
					<Reference X="0.000000" Y="0.000000" Z="0.000000"/>
				</Position>
			</Node>
		</ConnectionPoints>
	</PipeSupport>
	<PipeSupport ID="XMP_15" Specification="1C0JL" StockNumber="PDS-2-200">
		<Position>
			<Location X="596999.990000" Y="1510599.830000" Z="5204.870000"/>
			<Axis X="0.000000" Y="0.000000" Z="0.000000"/>
			<Reference X="0.000000" Y="0.000000" Z="0.000000"/>
		</Position>
		<Association Type="is associated with" ItemID="XMP_18"/>
		<NominalDiameter Value="2.000000" Units="in"/>
		<ConnectionPoints NumPoints="1">
			<Node>
				<Position>
					<Location X="596999.990000" Y="1510599.830000" Z="5204.870000"/>
					<Axis X="0.000000" Y="0.000000" Z="0.000000"/>
					<Reference X="0.000000" Y="0.000000" Z="0.000000"/>
				</Position>
			</Node>
		</ConnectionPoints>
	</PipeSupport>
	<PipeSupport ID="XMP_17" Specification="1C0JL" StockNumber="GST-1">
		<Position>
			<Location X="596999.990000" Y="1510664.820000" Z="5204.900000"/>
			<Axis X="0.000000" Y="0.000000" Z="0.000000"/>
			<Reference X="0.000000" Y="0.000000" Z="0.000000"/>
		</Position>
		<Association Type="is associated with" ItemID="XMP_18"/>
		<NominalDiameter Value="2.000000" Units="in"/>
		<ConnectionPoints NumPoints="1">
			<Node>
				<Position>
					<Location X="596999.990000" Y="1510664.820000" Z="5204.900000"/>
					<Axis X="0.000000" Y="0.000000" Z="0.000000"/>
					<Reference X="0.000000" Y="0.000000" Z="0.000000"/>
				</Position>
			</Node>
		</ConnectionPoints>
	</PipeSupport>
	<PipeSupport ID="XMP_48" Specification="1C0JL" StockNumber="GST-1">
		<Position>
			<Location X="597485.120000" Y="1511500.030000" Z="5205.010000"/>
			<Axis X="0.000000" Y="0.000000" Z="0.000000"/>
			<Reference X="0.000000" Y="0.000000" Z="0.000000"/>
		</Position>
		<Association Type="is associated with" ItemID="XMP_47"/>
		<NominalDiameter Value="2.000000" Units="in"/>
		<ConnectionPoints NumPoints="1">
			<Node>
				<Position>
					<Location X="597485.120000" Y="1511500.030000" Z="5205.010000"/>
					<Axis X="0.000000" Y="0.000000" Z="0.000000"/>
					<Reference X="0.000000" Y="0.000000" Z="0.000000"/>
				</Position>
			</Node>
		</ConnectionPoints>
	</PipeSupport>
	<PipeSupport ID="XMP_53" Specification="1C0JL" StockNumber="12-2-07-PE">
		<Position>
			<Location X="597750.120000" Y="1511500.030000" Z="5205.010000"/>
			<Axis X="0.000000" Y="0.000000" Z="0.000000"/>
			<Reference X="0.000000" Y="0.000000" Z="0.000000"/>
		</Position>
		<Association Type="is associated with" ItemID="XMP_52"/>
		<NominalDiameter Value="2.000000" Units="in"/>
		<ConnectionPoints NumPoints="1">
			<Node>
				<Position>
					<Location X="597750.120000" Y="1511500.030000" Z="5205.010000"/>
					<Axis X="0.000000" Y="0.000000" Z="0.000000"/>
					<Reference X="0.000000" Y="0.000000" Z="0.000000"/>
				</Position>
			</Node>
		</ConnectionPoints>
	</PipeSupport>
</PlantModel>
